imtoolkit/ADSMCode.py
imtoolkit/ANMCode.py
imtoolkit/AWGNChannel.py
imtoolkit/Basis.py
imtoolkit/Channel.py
imtoolkit/ChaosBasis.py
imtoolkit/ChaosUtil.py
imtoolkit/CoherentMLDSimulator.py
imtoolkit/DiagonalUnitaryCode.py
imtoolkit/DifferentialMLDSimulator.py
imtoolkit/IMCode.py
imtoolkit/IMUtil.py
imtoolkit/IdealOFDMChannel.py
imtoolkit/IdealRayleighChannel.py
imtoolkit/IdealRicianChannel.py
imtoolkit/Modulator.py
imtoolkit/NonSquareDifferentialChaosMLDSimulator.py
imtoolkit/NonSquareDifferentialMLDSimulator.py
imtoolkit/OSTBCode.py
imtoolkit/Parameters.py
imtoolkit/SemiUnitaryDifferentialMLDSimulator.py
imtoolkit/Simulator.py
imtoolkit/SymbolCode.py
imtoolkit/TASTCode.py
imtoolkit/Util.py
imtoolkit/__init__.py
imtoolkit/imsearch.py
imtoolkit/imtoolkit.py
imtoolkit/inds/M=2_K=1_Q=2_minh=2_ineq=0.txt
imtoolkit/inds/M=4_K=1_Q=4_minh=2_ineq=0.txt
imtoolkit-0.8.dist-info/LICENSE
imtoolkit-0.8.dist-info/METADATA
imtoolkit-0.8.dist-info/WHEEL
imtoolkit-0.8.dist-info/entry_points.txt
imtoolkit-0.8.dist-info/top_level.txt
imtoolkit-0.8.dist-info/RECORD
