Metadata-Version: 2.1
Name: imtoolkit
Version: 0.8
Summary: IMToolkit: An open-source index modulation toolkit for reproducible research based on massively parallel algorithms
Home-page: https://ishikawa.cc/imtoolkit/
Author: Naoki Ishikawa
Author-email: contact@ishikawa.cc
License: MIT
Download-URL: https://pypi.org/project/imtoolkit/
Platform: UNKNOWN
Classifier: License :: OSI Approved :: MIT License
Classifier: Programming Language :: Python :: 3.7
Requires-Dist: numpy
Requires-Dist: pandas
Requires-Dist: scipy
Requires-Dist: sympy
Requires-Dist: numba
Requires-Dist: tqdm
